setup.cfg
setup.py
hchk/__init__.py
hchk/cli.py
hchk.egg-info/PKG-INFO
hchk.egg-info/SOURCES.txt
hchk.egg-info/dependency_links.txt
hchk.egg-info/entry_points.txt
hchk.egg-info/not-zip-safe
hchk.egg-info/requires.txt
hchk.egg-info/top_level.txt